<beans xmlns="http://www.springframework.org/schema/beans"
	xmlns:xsi="http://www.w3.org/2001/XMLSchema-instance"
	xmlns:jaxws="http://cxf.apache.org/jaxws"
	xmlns:osgi="http://www.springframework.org/schema/osgi"
	xsi:schemaLocation="http://www.springframework.org/schema/beans http://www.springframework.org/schema/beans/spring-beans-2.5.xsd
		http://www.springframework.org/schema/context http://www.springframework.org/schema/context/spring-context-2.5.xsd
		http://cxf.apache.org/core http://cxf.apache.org/schemas/core.xsd
		http://cxf.apache.org/jaxws http://cxf.apache.org/schemas/jaxws.xsd
		http://www.springframework.org/schema/osgi http://www.springframework.org/schema/osgi/spring-osgi.xsd
	">

	<import resource="classpath:META-INF/cxf/cxf.xml" />
	<import resource="classpath:META-INF/cxf/cxf-extension-soap.xml" />
	<import resource="classpath:META-INF/cxf/cxf-extension-http.xml" />

    <!-- Configure based on a reference to an actual defined STSClient bean -->
    <bean id="stsClient" 
    	class="org.apache.cxf.ws.security.trust.STSClient">
    	<constructor-arg ref="cxf"/>
    	<property name="wsdlLocation" value="model/ws-trust-1.4-service.wsdl"/>
    	<property name="serviceName" value="{http://docs.oasis-open.org/ws-sx/ws-trust/200512/wsdl}SecurityTokenServiceProvider"/>
    	<property name="endpointName" value="{http://docs.oasis-open.org/ws-sx/ws-trust/200512/wsdl}SecurityTokenServiceSOAP"/>
    	<property name="requiresEntropy" value="false" />
    </bean>

    <bean class="org.apache.esb.sts.client.Invoker">
    	<property name="stsClient" ref="stsClient"/>
    </bean>

</beans>